sopsy/__init__.py
sopsy/errors.py
sopsy/py.typed
sopsy/sopsy.py
sopsy/utils.py
sopsy-1.2.1.dist-info/METADATA
sopsy-1.2.1.dist-info/WHEEL
sopsy-1.2.1.dist-info/licenses/LICENSE
sopsy-1.2.1.dist-info/RECORD
