Metadata-Version: 2.4
Name: sopsy
Version: 1.2.1
Summary: SOPS Python wrapper library
Project-URL: Changelog, https://sopsy.nikaro.net/changelog/
Project-URL: Homepage, https://sopsy.nikaro.net
Project-URL: Issues, https://github.com/nikaro/sopsy/issues
Project-URL: Repository, https://github.com/nikaro/sopsy
Author-email: Nicolas Karolak <nicolas@karolak.fr>
License: MIT
License-File: LICENSE
Keywords: sops
Classifier: Development Status :: 5 - Production/Stable
Classifier: Intended Audience :: Developers
Classifier: Intended Audience :: System Administrators
Classifier: License :: OSI Approved :: MIT License
Classifier: Operating System :: OS Independent
Classifier: Programming Language :: Python :: 3
Classifier: Topic :: Security :: Cryptography
Classifier: Topic :: Software Development :: Libraries :: Python Modules
Classifier: Typing :: Typed
Requires-Python: >=3.8
Requires-Dist: pyyaml>=6.0.1
